apal_client/__init__.py
apal_client/client.py
apal_client/exceptions.py
apal_client-0.1.0.dist-info/METADATA
apal_client-0.1.0.dist-info/WHEEL
apal_client-0.1.0.dist-info/top_level.txt
apal_client-0.1.0.dist-info/RECORD
